portwine/__init__.py
portwine/analyzers/__init__.py
portwine/analyzers/base.py
portwine/analyzers/bootstrap.py
portwine/analyzers/correlation.py
portwine/analyzers/downsidecorrelation.py
portwine/analyzers/drawdownflattener.py
portwine/analyzers/edgedecay.py
portwine/analyzers/equitydrawdown.py
portwine/analyzers/gridequitydrawdown.py
portwine/analyzers/montecarlo.py
portwine/analyzers/noiserobustness.py
portwine/analyzers/optimalleverage.py
portwine/analyzers/performanceattribution.py
portwine/analyzers/positionsizing.py
portwine/analyzers/regimechange.py
portwine/analyzers/riskcontribution.py
portwine/analyzers/seasonality.py
portwine/analyzers/shock.py
portwine/analyzers/strategycomparison.py
portwine/analyzers/studentttest.py
portwine/analyzers/tickerrisk.py
portwine/analyzers/traintest.py
portwine/analyzers/transactioncost.py
portwine/analyzers/walkforward.py
portwine/backtester.py
portwine/brokers/__init__.py
portwine/brokers/alpaca.py
portwine/brokers/base.py
portwine/brokers/mock.py
portwine/execution.py
portwine/indexes.py
portwine/loaders/__init__.py
portwine/loaders/alpaca.py
portwine/loaders/alternative.py
portwine/loaders/barchartindices.py
portwine/loaders/base.py
portwine/loaders/broker.py
portwine/loaders/dailytoopenclose.py
portwine/loaders/eodhd.py
portwine/loaders/fred.py
portwine/loaders/noisy.py
portwine/loaders/polygon.py
portwine/logging.py
portwine/optimizer.py
portwine/scheduler.py
portwine/strategies/__init__.py
portwine/strategies/base.py
portwine/strategies/rprtstrategy.py
portwine/strategies/simple_moving_average.py
portwine/vectorized.py
portwine-0.1.3.dist-info/METADATA
portwine-0.1.3.dist-info/WHEEL
portwine-0.1.3.dist-info/RECORD
