Metadata-Version: 2.1
Name: portwine
Version: 0.1.3
Summary: A clean, elegant portfolio backtester that simplifies strategy development with online processing and comprehensive analysis tools
Author: Stuart Farmer
Author-email: stuart@lamden.io
Requires-Python: >=3.10,<4.0
Classifier: Programming Language :: Python :: 3
Classifier: Programming Language :: Python :: 3.10
Classifier: Programming Language :: Python :: 3.11
Classifier: Programming Language :: Python :: 3.12
Requires-Dist: cvxpy (>=1.6.4,<2.0.0)
Requires-Dist: django-scheduler (>=0.10.1,<0.11.0)
Requires-Dist: fastparquet (>=2024.2.0,<2025.0.0)
Requires-Dist: flask (>=3.1.0,<4.0.0)
Requires-Dist: fredapi (>=0.5.2,<0.6.0)
Requires-Dist: freezegun (>=1.5.1,<2.0.0)
Requires-Dist: matplotlib (>=3.10.1,<4.0.0)
Requires-Dist: numba (>=0.61.2,<0.62.0)
Requires-Dist: pandas (>=2.2.3,<3.0.0)
Requires-Dist: pandas-market-calendars (>=5.0.0,<6.0.0)
Requires-Dist: pytz (>=2024.1,<2025.0)
Requires-Dist: requests (>=2.31.0,<3.0.0)
Requires-Dist: rich (>=14.0.0,<15.0.0)
Requires-Dist: scipy (>=1.15.2,<2.0.0)
Requires-Dist: statsmodels (>=0.14.4,<0.15.0)
Requires-Dist: tqdm (>=4.67.1,<5.0.0)
